schema2md/__init__.py
schema2md/cli.py
schema2md/contexts.py
schema2md/declarations.py
schema2md/format_funcs.py
schema2md/parsers.py
schema2md/reference.py
schema2md/tab.py
schema2md-0.0.9.dist-info/METADATA
schema2md-0.0.9.dist-info/WHEEL
schema2md-0.0.9.dist-info/entry_points.txt
schema2md-0.0.9.dist-info/top_level.txt
schema2md-0.0.9.dist-info/RECORD
